[
  {
    "Id": 1,
    "TraitId": "DI01",
    "Title": "Conjurer",
    "Description": "Illusions, traps, minions -- you boldly tap into the arcana to summon something from nothing.",
    "Personality": "Bravery",
    "Training": "Magic"
  },
  {
    "Id": 2,
    "TraitId": "DI02",
    "Title": "Enchanter",
    "Description": "Use the arcane to bring life to the mundane by bewitching, empowering, and ensorcelling.",
    "Personality": "Wit",
    "Training": "Magic"
  },
  {
    "Id": 3,
    "TraitId": "DI03",
    "Title": "Warlock",
    "Description": "You yield the arcane like a soldier wields a sword: with both force and destructive grace.",
    "Personality": "Strength",
    "Training": "Magic"
  },
  {
    "Id": 4,
    "TraitId": "DI04",
    "Title": "Philosopher",
    "Description": "You seek to further understand the secrets of the universe, and to pass those insights on",
    "Personality": "Bravery",
    "Training": "Rhetoric"
  },
  {
    "Id": 5,
    "TraitId": "DI05",
    "Title": "Tactician",
    "Description": "The mechanics of the battlefield are your expertise. Use cunning and strategy to lead your soldiers to victory.",
    "Personality": "Wit",
    "Training": "Rhetoric"
  },
  {
    "Id": 6,
    "TraitId": "DI06",
    "Title": "Pioneer",
    "Description": "You trailblaze through the wilds, helping your people to overcome dangers both natural and man-made.",
    "Personality": "Strength",
    "Training": "Rhetoric"
  },
  {
    "Id": 7,
    "TraitId": "DI07",
    "Title": "Druid",
    "Description": "You live your life as a rogue and outsider -- one with an uncommon bond with nature, even using it to change your form.",
    "Personality": "Bravery",
    "Training": "Stealth"
  },
  {
    "Id": 8,
    "TraitId": "DI08",
    "Title": "Bard",
    "Description": "With word, song, and theater, you both entertain and inspire those around you.",
    "Personality": "Wit",
    "Training": "Stealth"
  },
  {
    "Id": 9,
    "TraitId": "DI09",
    "Title": "Rogue",
    "Description": "You use cunning, finesse, and treachery to take manipulate your surroundings to your advantage.",
    "Personality": "Strength",
    "Training": "Stealth"
  },
  {
    "Id": 10,
    "TraitId": "DI10",
    "Title": "Soldier",
    "Description": "Discipline and strength make you a destructive force on the battlefield, and a leader off it.",
    "Personality": "Bravery",
    "Training": "Warfare"
  },
  {
    "Id": 11,
    "TraitId": "DI11",
    "Title": "Knight",
    "Description": "Using your might and virtue, you fight for your noble cause with relentless zeal.",
    "Personality": "Wit",
    "Training": "Warfare"
  },
  {
    "Id": 12,
    "TraitId": "DI12",
    "Title": "Barbarian",
    "Description": "Where other fighters restrain themselves in the name of honor, you bring a terrifying frenzy and bloodlust.",
    "Personality": "Strength",
    "Training": "Warfare"
  }
]